LICENSE.md
MANIFEST.in
README.md
setup.py
django_theme_material_kit.egg-info/PKG-INFO
django_theme_material_kit.egg-info/SOURCES.txt
django_theme_material_kit.egg-info/dependency_links.txt
django_theme_material_kit.egg-info/not-zip-safe
django_theme_material_kit.egg-info/top_level.txt
docs/blank.txt
theme_material_kit/__init__.py
theme_material_kit/admin.py
theme_material_kit/apps.py
theme_material_kit/forms.py
theme_material_kit/models.py
theme_material_kit/tests.py
theme_material_kit/urls.py
theme_material_kit/utils.py
theme_material_kit/views.py
theme_material_kit/migrations/0001_initial.py
theme_material_kit/migrations/0002_delete_test.py
theme_material_kit/migrations/__init__.py
theme_material_kit/static/css/forms.css
theme_material_kit/static/css/material-kit.css
theme_material_kit/static/css/material-kit.css.map
theme_material_kit/static/css/material-kit.min.css
theme_material_kit/static/css/nucleo-icons.css
theme_material_kit/static/css/nucleo-svg.css
theme_material_kit/static/css/widgets.css
theme_material_kit/static/fonts/nucleo-icons.eot
theme_material_kit/static/fonts/nucleo-icons.svg
theme_material_kit/static/fonts/nucleo-icons.ttf
theme_material_kit/static/fonts/nucleo-icons.woff
theme_material_kit/static/fonts/nucleo-icons.woff2
theme_material_kit/static/fonts/nucleo.eot
theme_material_kit/static/fonts/nucleo.ttf
theme_material_kit/static/fonts/nucleo.woff
theme_material_kit/static/fonts/nucleo.woff2
theme_material_kit/static/img/apple-icon.png
theme_material_kit/static/img/bg.jpg
theme_material_kit/static/img/bg0.jpg
theme_material_kit/static/img/bg10.jpg
theme_material_kit/static/img/bg2.jpg
theme_material_kit/static/img/bg3.jpg
theme_material_kit/static/img/bg5.jpg
theme_material_kit/static/img/bg9.jpg
theme_material_kit/static/img/bruce-mars.jpg
theme_material_kit/static/img/city-profile.jpg
theme_material_kit/static/img/down-arrow-dark.svg
theme_material_kit/static/img/down-arrow-white.svg
theme_material_kit/static/img/down-arrow.svg
theme_material_kit/static/img/favicon.png
theme_material_kit/static/img/ivana-square.jpg
theme_material_kit/static/img/ivana-squares.jpg
theme_material_kit/static/img/logo-ct-dark.png
theme_material_kit/static/img/macbook.png
